README.md
setup.cfg
setup.py
ald_distributions/Binomialdistribution.py
ald_distributions/Gaussiandistribution.py
ald_distributions/Generaldistribution.py
ald_distributions/__init__.py
ald_distributions.egg-info/PKG-INFO
ald_distributions.egg-info/SOURCES.txt
ald_distributions.egg-info/dependency_links.txt
ald_distributions.egg-info/not-zip-safe
ald_distributions.egg-info/top_level.txt